TeleMed_test/__init__.py
TeleMed_test/algorithms/__init__.py
TeleMed_test/algorithms/experiment.py
TeleMed_test/algorithms/job.py
TeleMed_test/algorithms/models.py
TeleMed_test/algorithms/reconcile.py
TeleMed_test/algorithms/utils.py
TeleMed_test/analytics/__init__.py
TeleMed_test/analytics/evaluationMetrics.py
TeleMed_test/datahandler/__init__.py
TeleMed_test/datahandler/datahandler.py
TeleMed_test/datapreparation/__init__.py
TeleMed_test/datapreparation/model_preproc.py
TeleMed_test/datapreparation/preprocessing.py
TeleMed_test/datapreparation/uc_preproc.py
TeleMed_test/datapreparation/utils.py
TeleMed_test/dataset/__init__.py
TeleMed_test/datavisualization/__init__.py
TeleMed_test/datavisualization/plotPrediction.py
TeleMed_test/datavisualization/timeSeriesVisualization.py
TeleMed_test/datavisualization/visualization.py
TeleMed_test/utility/__init__.py
TeleMed_test/utility/check_utils.py
TeleMed_test/utility/configuration_utils.py
TeleMed_test/utility/constants.py
TeleMed_test/utility/exceptions.py
TeleMed_test/utility/resources.py
TeleMed_test/utility/tele_logger.py
TeleMed_test-1.0.0.dist-info/METADATA
TeleMed_test-1.0.0.dist-info/WHEEL
TeleMed_test-1.0.0.dist-info/top_level.txt
TeleMed_test-1.0.0.dist-info/RECORD
